{
    "Ar36": {
        "error": 0.00081465317694108682, 
        "fit": "parabolic", 
        "value": 0.00078454627563946525
    }, 
    "Ar37": {
        "error": 0.12978141109673641, 
        "fit": "linear", 
        "value": -0.021504695691449208
    }, 
    "Ar38": {
        "error": 0.12318224411175521, 
        "fit": "linear", 
        "value": -0.099938131861340485
    }, 
    "Ar39": {
        "error": 0.0058095260211501864, 
        "fit": "parabolic", 
        "value": 0.027945068245295822
    }, 
    "Ar40": {
        "error": 0.1270773889147542, 
        "fit": "parabolic", 
        "value": 0.28067151646888733
    }, 
    "Ar41": {
        "error": 0.12589251234698637, 
        "fit": "average_SEM", 
        "value": -0.040695722802774982
    }
}