{
    "AX": {
        "error": 0.058499854910267456, 
        "fit": "average_SEM", 
        "value": -0.0047587980962513635
    }, 
    "CDD": {
        "error": 1.4192347150643278e-05, 
        "fit": "average_SEM", 
        "value": 1.295578113058582e-06
    }, 
    "H1": {
        "error": 0.13925702810475465, 
        "fit": "average_SEM", 
        "value": 0.014974419997694591
    }, 
    "H2": {
        "error": 0.12092905300125088, 
        "fit": "average_SEM", 
        "value": -0.09289125763461925
    }, 
    "L1": {
        "error": 0.13345436796829857, 
        "fit": "average_SEM", 
        "value": -0.054389311680643
    }, 
    "L2": {
        "error": 0.1311910837087382, 
        "fit": "average_SEM", 
        "value": -0.024332488665822893
    }
}