{
    "Ar36": {
        "error": 0.0016632026156416597, 
        "fit": "parabolic", 
        "value": 0.0087348286840196309
    }, 
    "Ar37": {
        "error": 0.14192387702427287, 
        "fit": "linear", 
        "value": -0.0059435855248221436
    }, 
    "Ar38": {
        "error": 0.12599299035892508, 
        "fit": "linear", 
        "value": 0.040072639514673505
    }, 
    "Ar39": {
        "error": 0.061550605249194805, 
        "fit": "parabolic", 
        "value": 7.8392983412140795
    }, 
    "Ar40": {
        "error": 0.45373935322344472, 
        "fit": "parabolic", 
        "value": 1416.0034571945375
    }, 
    "Ar41": {
        "error": 0.14110901311491902, 
        "fit": "average_SEM", 
        "value": -0.049994455851992824
    }
}