{
    "Ar36": {
        "error": 0.0019241992739917864, 
        "fit": "parabolic", 
        "value": 0.013767892698399222
    }, 
    "Ar37": {
        "error": 0.14495222468003366, 
        "fit": "linear", 
        "value": 0.013485368197252505
    }, 
    "Ar38": {
        "error": 0.13151275254888575, 
        "fit": "linear", 
        "value": 0.08846096665528061
    }, 
    "Ar39": {
        "error": 0.065782396701981063, 
        "fit": "parabolic", 
        "value": 12.125682796073677
    }, 
    "Ar40": {
        "error": 0.55848662799623361, 
        "fit": "parabolic", 
        "value": 2185.8260960656771
    }, 
    "Ar41": {
        "error": 0.13776864945957479, 
        "fit": "average_SEM", 
        "value": -0.019772950889891946
    }
}