{
    "AX": {
        "error": 0.05151585751388096, 
        "fit": "average_SEM", 
        "value": -0.03560853866236155
    }, 
    "CDD": {
        "error": 0.0001314825174102767, 
        "fit": "average_SEM", 
        "value": 0.00010537368749889235
    }, 
    "H1": {
        "error": 0.12554689850872047, 
        "fit": "average_SEM", 
        "value": 0.05098956687369435
    }, 
    "H2": {
        "error": 0.16309691465243106, 
        "fit": "average_SEM", 
        "value": -0.34799290111081466
    }, 
    "L1": {
        "error": 0.12652486451827066, 
        "fit": "average_SEM", 
        "value": -0.07859021718613804
    }, 
    "L2": {
        "error": 0.14431072980582804, 
        "fit": "average_SEM", 
        "value": -0.06353707280876632
    }
}